{"errors":[],"warnings":[],"namedChunkGroups":{"polyfill":{"chunks":[2,0,7],"assets":["webpack-runtime-562d6876b228896ff7f2.js","webpack-runtime-562d6876b228896ff7f2.js.map","commons-6f97deec0c15a1e682e1.js","commons-6f97deec0c15a1e682e1.js.map","polyfill-79abd7c50267fa169289.js","polyfill-79abd7c50267fa169289.js.map"],"children":{},"childAssets":{}},"app":{"chunks":[2,1,6,3],"assets":["webpack-runtime-562d6876b228896ff7f2.js","webpack-runtime-562d6876b228896ff7f2.js.map","styles.484871997babf02b273d.css","styles-e9d24b1846c7d6eb9685.js","styles-e9d24b1846c7d6eb9685.js.map","framework-d585a04b7d285a7760d6.js","framework-d585a04b7d285a7760d6.js.map","app-85b664384dfb2eaa0564.js","app-85b664384dfb2eaa0564.js.map"],"children":{},"childAssets":{}},"component---src-pages-index-js":{"chunks":[1,0,4],"assets":["styles.484871997babf02b273d.css","styles-e9d24b1846c7d6eb9685.js","styles-e9d24b1846c7d6eb9685.js.map","commons-6f97deec0c15a1e682e1.js","commons-6f97deec0c15a1e682e1.js.map","component---src-pages-index-js-f53e69017365cc9ce8c6.js","component---src-pages-index-js-f53e69017365cc9ce8c6.js.map"],"children":{},"childAssets":{}},"component---src-templates-blog-post-js":{"chunks":[1,0,5],"assets":["styles.484871997babf02b273d.css","styles-e9d24b1846c7d6eb9685.js","styles-e9d24b1846c7d6eb9685.js.map","commons-6f97deec0c15a1e682e1.js","commons-6f97deec0c15a1e682e1.js.map","component---src-templates-blog-post-js-5344c1e69bac2cdb94df.js","component---src-templates-blog-post-js-5344c1e69bac2cdb94df.js.map"],"children":{},"childAssets":{}}},"assetsByChunkName":{"polyfill":["webpack-runtime-562d6876b228896ff7f2.js","commons-6f97deec0c15a1e682e1.js","polyfill-79abd7c50267fa169289.js"],"app":["webpack-runtime-562d6876b228896ff7f2.js","styles.484871997babf02b273d.css","styles-e9d24b1846c7d6eb9685.js","framework-d585a04b7d285a7760d6.js","app-85b664384dfb2eaa0564.js"],"component---src-pages-index-js":["styles.484871997babf02b273d.css","styles-e9d24b1846c7d6eb9685.js","commons-6f97deec0c15a1e682e1.js","component---src-pages-index-js-f53e69017365cc9ce8c6.js"],"component---src-templates-blog-post-js":["styles.484871997babf02b273d.css","styles-e9d24b1846c7d6eb9685.js","commons-6f97deec0c15a1e682e1.js","component---src-templates-blog-post-js-5344c1e69bac2cdb94df.js"]}}